pos/__init__.py
pos/arbol_del_pan.py
pos/jardin.py
pos/loggro.py
pos/util.py
pos/wilborada.py
pos_datasketch-0.1.5.dist-info/METADATA
pos_datasketch-0.1.5.dist-info/WHEEL
pos_datasketch-0.1.5.dist-info/RECORD
